solt/__init__.py
solt/constants/__init__.py
solt/constants/_constants.py
solt/core/__init__.py
solt/core/_base_transforms.py
solt/core/_core.py
solt/core/_data.py
solt/transforms/__init__.py
solt/transforms/_transforms.py
solt/utils/__init__.py
solt/utils/_utils.py
solt-0.2.1.dist-info/licenses/LICENSE
solt-0.2.1.dist-info/METADATA
solt-0.2.1.dist-info/WHEEL
solt-0.2.1.dist-info/top_level.txt
solt-0.2.1.dist-info/RECORD
